setup.py
z_ml_utils.egg-info/PKG-INFO
z_ml_utils.egg-info/SOURCES.txt
z_ml_utils.egg-info/dependency_links.txt
z_ml_utils.egg-info/not-zip-safe
z_ml_utils.egg-info/requires.txt
z_ml_utils.egg-info/top_level.txt
zmodel/__init__.py
zmodel/xgb.py