Metadata-Version: 1.0
Name: z-ml-utils
Version: 0.1
Summary: A collection of machine learning functions for Python model making
Home-page: http://github.com/zthoutt/ml-utils
Author: Zack Thoutt
Author-email: zackarey.thoutt@colorado.edu
License: MIT
Platform: UNKNOWN
